setup.py
camli/__init__.py
camli/op.py
camli/schema.py
camli/schema_test.py
camlistore_client.egg-info/PKG-INFO
camlistore_client.egg-info/SOURCES.txt
camlistore_client.egg-info/dependency_links.txt
camlistore_client.egg-info/requires.txt
camlistore_client.egg-info/top_level.txt