Metadata-Version: 1.0
Name: camlistore-client
Version: 1.0.2dev
Summary: Client library for Camlistore.
Home-page: http://camlistore.org
Author: Brett Slatkin
Author-email: bslatkin@gmail.com
License: Apache v2
Platform: UNKNOWN
Classifier: Environment :: Console
Classifier: Topic :: Internet :: WWW/HTTP
